{
  "cookies": [
    {
      "name": "session-username",
      "value": "visual_user",
      "domain": "www.saucedemo.com",
      "path": "/",
      "expires": 1780914797,
      "httpOnly": false,
      "secure": false,
      "sameSite": "Lax"
    }
  ],
  "origins": [
    {
      "origin": "https://www.saucedemo.com",
      "localStorage": [
        {
          "name": "backtrace-guid",
          "value": "f42c5134-e62e-473b-a769-b6c6b7766e1f"
        },
        {
          "name": "backtrace-last-active",
          "value": "1780914196797"
        }
      ]
    }
  ]
}